utils/__init__.py
utils/thread.py
async_dispatcher-1.2.5.dist-info/METADATA
async_dispatcher-1.2.5.dist-info/WHEEL
async_dispatcher-1.2.5.dist-info/top_level.txt
async_dispatcher-1.2.5.dist-info/RECORD
