Metadata-Version: 2.1
Name: async-dispatcher
Version: 1.2.5
Requires-Dist: aiohttp ==3.9.3
Requires-Dist: aiosignal ==1.3.1
Requires-Dist: async-timeout ==4.0.3
Requires-Dist: attrs ==23.2.0
Requires-Dist: certifi ==2024.2.2
Requires-Dist: charset-normalizer ==3.3.2
Requires-Dist: docutils ==0.20.1
Requires-Dist: frozenlist ==1.4.1
Requires-Dist: idna ==3.6
Requires-Dist: importlib-metadata ==7.0.1
Requires-Dist: jaraco.classes ==3.3.0
Requires-Dist: keyring ==24.3.0
Requires-Dist: markdown-it-py ==3.0.0
Requires-Dist: mdurl ==0.1.2
Requires-Dist: more-itertools ==10.2.0
Requires-Dist: multidict ==6.0.5
Requires-Dist: nh3 ==0.2.15
Requires-Dist: pkginfo ==1.9.6
Requires-Dist: Pygments ==2.17.2
Requires-Dist: pywin32-ctypes ==0.2.2
Requires-Dist: readme-renderer ==42.0
Requires-Dist: requests ==2.31.0
Requires-Dist: requests-toolbelt ==1.0.0
Requires-Dist: rfc3986 ==2.0.0
Requires-Dist: rich ==13.7.0
Requires-Dist: twine ==4.0.2
Requires-Dist: urllib3 ==2.2.0
Requires-Dist: yarl ==1.9.4
Requires-Dist: zipp ==3.17.0
